setup.py
montecarlo/__init__.py
montecarlo/montecarlo.py
montecarlo.egg-info/PKG-INFO
montecarlo.egg-info/SOURCES.txt
montecarlo.egg-info/dependency_links.txt
montecarlo.egg-info/top_level.txt