Metadata-Version: 1.1
Name: montecarlo
Version: 0.1.4
Summary: A small Python library for creating simple Monte Carlo simulations.
Home-page: https://github.com/csu/pymontecarlo
Author: Christopher Su
Author-email: chris+gh@christopher.su
License: UNKNOWN
Download-URL: https://github.com/csu/pymontecarlo/archive/master.zip
Platform: UNKNOWN
